grafanacli/__init__.py
grafanacli-1.0.10.dist-info/LICENSE
grafanacli-1.0.10.dist-info/METADATA
grafanacli-1.0.10.dist-info/WHEEL
grafanacli-1.0.10.dist-info/top_level.txt
grafanacli-1.0.10.dist-info/RECORD
