Metadata-Version: 2.1
Name: grafanacli
Version: 1.0.10
Summary: Library to manage Grafana API
Home-page: https://github.com/JeferCatarina/grafanacli
Author: Jeferson Catarina
Author-email: catarinajeferson@gmail.com
License: MIT
Platform: UNKNOWN
Classifier: Development Status :: 3 - Alpha
Classifier: Intended Audience :: Developers
Classifier: Intended Audience :: System Administrators
Classifier: Topic :: Internet
Classifier: Topic :: System :: Monitoring
Classifier: Topic :: Software Development :: Libraries :: Python Modules
Classifier: Operating System :: OS Independent
Classifier: License :: OSI Approved :: MIT License
Classifier: Programming Language :: Python :: 2
Classifier: Programming Language :: Python :: 2.7
Classifier: Programming Language :: Python :: 3
Classifier: Programming Language :: Python :: 3.6
Requires-Dist: requests
